README.md
setup.cfg
setup.py
py_archy/__init__.py
py_archy/py_archy.py
py_archy.egg-info/PKG-INFO
py_archy.egg-info/SOURCES.txt
py_archy.egg-info/dependency_links.txt
py_archy.egg-info/not-zip-safe
py_archy.egg-info/top_level.txt