Metadata-Version: 1.1
Name: py-archy
Version: 1.0.2
Summary: Implementation of the popular node-archy tool in python
Home-page: https://github.com/dcdanko/pyarchy
Author: David C. Danko
Author-email: dcdanko@gmail.com
License: MIT license
Keywords: pyarchy
Platform: UNKNOWN
Classifier: Intended Audience :: Developers
Classifier: License :: OSI Approved :: MIT License
Classifier: Natural Language :: English
Classifier: Programming Language :: Python :: 3
